<?xml version="1.0" encoding="utf-8" ?>
<dwsync>
<file name="script.js" server="www.birtas.ro/public_html/" local="130698623049574799" remote="130698622800000000" Dst="1" />
<file name="jquery.datetimepicker.js" server="www.birtas.ro/public_html/" local="130679617864423828" remote="130679617200000000" Dst="1" />
<file name="script.js" server="freeex.activewatch.ro" local="130912271886536459" remote="130912199400000000" Dst="1" />
<file name="jquery.datetimepicker.js" server="freeex.activewatch.ro" local="130815526002549474" remote="130815417600000000" Dst="2" />
<file name="jquery-migrate-1.2.1.min.js" server="freeex.activewatch.ro" local="130803417972270635" remote="130803309600000000" Dst="2" />
<file name="jquery-2.0.3.min.js" server="freeex.activewatch.ro" local="130803417864786446" remote="130803309600000000" Dst="2" />
<file name="jquery-ui.js" server="freeex.activewatch.ro" local="130912239567695164" remote="130912167000000000" Dst="1" />
<file name="datepicker-ro.js" server="freeex.activewatch.ro" local="130815525651789411" remote="130815417600000000" Dst="2" />
<file name="jquery-ui-timepicker-addon.js" server="freeex.activewatch.ro" local="130872494098654801" remote="130872385800000000" Dst="2" />
</dwsync>